yamdl/__init__.py
yamdl/apps.py
yamdl/loader.py
yamdl/router.py
yamdl-1.0.0.dist-info/METADATA
yamdl-1.0.0.dist-info/WHEEL
yamdl-1.0.0.dist-info/top_level.txt
yamdl-1.0.0.dist-info/RECORD
