Metadata-Version: 2.1
Name: yamdl
Version: 1.0.0
Summary: Flat-file model instances for Django
Home-page: https://github.com/andrewgodwin/yamdl/
Author: Andrew Godwin
License: BSD
Classifier: Development Status :: 5 - Production/Stable
Classifier: Environment :: Web Environment
Classifier: Framework :: Django
Classifier: Intended Audience :: Developers
Classifier: License :: OSI Approved :: BSD License
Classifier: Operating System :: OS Independent
Classifier: Programming Language :: Python :: 3
Classifier: Topic :: Internet :: WWW/HTTP
Requires-Python: >=3.7
Requires-Dist: Django (>=3.2)
Requires-Dist: pyyaml (~=6.0)
